[{"alt":"© Nathan Richard","hiImgH":1657,"hiImgW":2500,"hiUrl":"/32_hu1952808372356292606.webp","index":31,"loImgH":530,"loImgW":800,"loUrl":"/32_hu11846540937672794432.webp"},{"alt":"© Nathan Richard","hiImgH":1667,"hiImgW":2500,"hiUrl":"/31_hu412487416006944580.webp","index":30,"loImgH":533,"loImgW":800,"loUrl":"/31_hu7058390478792411834.webp"},{"alt":"© Nathan Richard","hiImgH":1667,"hiImgW":2500,"hiUrl":"/30_hu14580092602594365019.webp","index":29,"loImgH":533,"loImgW":800,"loUrl":"/30_hu293854114022570772.webp"},{"alt":"© Nathan Richard","hiImgH":1667,"hiImgW":2500,"hiUrl":"/29_hu18201868051787927703.webp","index":28,"loImgH":533,"loImgW":800,"loUrl":"/29_hu3823959717455664559.webp"},{"alt":"© Nathan Richard","hiImgH":1667,"hiImgW":2500,"hiUrl":"/28_hu9498389596688357645.webp","index":27,"loImgH":533,"loImgW":800,"loUrl":"/28_hu7417030903221803572.webp"},{"alt":"© Nathan Richard","hiImgH":1667,"hiImgW":2500,"hiUrl":"/27_hu156921016715458240.webp","index":26,"loImgH":533,"loImgW":800,"loUrl":"/27_hu15159314299095165632.webp"},{"alt":"© Nathan Richard","hiImgH":1667,"hiImgW":2500,"hiUrl":"/26_hu18240809776509695818.webp","index":25,"loImgH":533,"loImgW":800,"loUrl":"/26_hu2369354063482763427.webp"},{"alt":"© Nathan Richard","hiImgH":3750,"hiImgW":2500,"hiUrl":"/25_hu10052562702293864387.webp","index":24,"loImgH":1200,"loImgW":800,"loUrl":"/25_hu2248253526296858972.webp"},{"alt":"© Nathan Richard","hiImgH":1657,"hiImgW":2500,"hiUrl":"/24_hu10568038407117531309.webp","index":23,"loImgH":530,"loImgW":800,"loUrl":"/24_hu4160435910919792000.webp"},{"alt":"© Nathan Richard","hiImgH":3772,"hiImgW":2500,"hiUrl":"/23_hu5292935061399960817.webp","index":22,"loImgH":1207,"loImgW":800,"loUrl":"/23_hu3006957936730962957.webp"},{"alt":"© Nathan Richard","hiImgH":1657,"hiImgW":2500,"hiUrl":"/22_hu16723488154429777677.webp","index":21,"loImgH":530,"loImgW":800,"loUrl":"/22_hu15035155557783100612.webp"},{"alt":"© Nathan Richard","hiImgH":1657,"hiImgW":2500,"hiUrl":"/21_hu10913788920535734275.webp","index":20,"loImgH":530,"loImgW":800,"loUrl":"/21_hu9948166988744817938.webp"},{"alt":"© Nathan Richard","hiImgH":3772,"hiImgW":2500,"hiUrl":"/20_hu6708297098185620628.webp","index":19,"loImgH":1207,"loImgW":800,"loUrl":"/20_hu5166539556022825031.webp"},{"alt":"© Nathan Richard","hiImgH":1657,"hiImgW":2500,"hiUrl":"/19_hu14565893741024209336.webp","index":18,"loImgH":530,"loImgW":800,"loUrl":"/19_hu4979725991946323933.webp"},{"alt":"© Nathan Richard","hiImgH":1657,"hiImgW":2500,"hiUrl":"/18_hu6508219887582133528.webp","index":17,"loImgH":530,"loImgW":800,"loUrl":"/18_hu1449501778260800746.webp"},{"alt":"© Nathan Richard","hiImgH":1657,"hiImgW":2500,"hiUrl":"/17_hu4049280793332055679.webp","index":16,"loImgH":530,"loImgW":800,"loUrl":"/17_hu12295046459299378588.webp"},{"alt":"© Nathan Richard","hiImgH":1657,"hiImgW":2500,"hiUrl":"/16_hu14489361782119784915.webp","index":15,"loImgH":530,"loImgW":800,"loUrl":"/16_hu642143731790110209.webp"},{"alt":"© Nathan Richard","hiImgH":3333,"hiImgW":2500,"hiUrl":"/15_hu7174207882287968856.webp","index":14,"loImgH":1067,"loImgW":800,"loUrl":"/15_hu13852566597577821427.webp"},{"alt":"© Nathan Richard","hiImgH":1875,"hiImgW":2500,"hiUrl":"/14_hu11854668100507977191.webp","index":13,"loImgH":600,"loImgW":800,"loUrl":"/14_hu13707300033696108468.webp"},{"alt":"© Nathan Richard","hiImgH":1875,"hiImgW":2500,"hiUrl":"/13_hu11479616551169610937.webp","index":12,"loImgH":600,"loImgW":800,"loUrl":"/13_hu13051411447933244486.webp"},{"alt":"© Nathan Richard","hiImgH":1875,"hiImgW":2500,"hiUrl":"/12_hu2441218285068231589.webp","index":11,"loImgH":600,"loImgW":800,"loUrl":"/12_hu12745077578284389033.webp"},{"alt":"© Nathan Richard","hiImgH":3333,"hiImgW":2500,"hiUrl":"/11_hu8383828792416205671.webp","index":10,"loImgH":1067,"loImgW":800,"loUrl":"/11_hu16393094567630492513.webp"},{"alt":"© Nathan Richard","hiImgH":1875,"hiImgW":2500,"hiUrl":"/10_hu18024486211170990555.webp","index":9,"loImgH":600,"loImgW":800,"loUrl":"/10_hu10553375654943767949.webp"},{"alt":"© Nathan Richard","hiImgH":3333,"hiImgW":2500,"hiUrl":"/09_hu17941956112658727553.webp","index":8,"loImgH":1067,"loImgW":800,"loUrl":"/09_hu1875852742449121237.webp"},{"alt":"© Nathan Richard","hiImgH":3765,"hiImgW":2500,"hiUrl":"/08_hu14932722052394880001.webp","index":7,"loImgH":1205,"loImgW":800,"loUrl":"/08_hu6147515378976212007.webp"},{"alt":"© Nathan Richard","hiImgH":3750,"hiImgW":2500,"hiUrl":"/07_hu13267759895807228255.webp","index":6,"loImgH":1200,"loImgW":800,"loUrl":"/07_hu13653955332776002999.webp"},{"alt":"© Nathan Richard","hiImgH":1667,"hiImgW":2500,"hiUrl":"/06_hu7036929645138063835.webp","index":5,"loImgH":533,"loImgW":800,"loUrl":"/06_hu10682654308246338039.webp"},{"alt":"© Nathan Richard","hiImgH":1667,"hiImgW":2500,"hiUrl":"/05_hu14322294766590362469.webp","index":4,"loImgH":533,"loImgW":800,"loUrl":"/05_hu16845739616895274995.webp"},{"alt":"© Nathan Richard","hiImgH":3750,"hiImgW":2500,"hiUrl":"/04_hu6601049288713658866.webp","index":3,"loImgH":1200,"loImgW":800,"loUrl":"/04_hu5305220410937972594.webp"},{"alt":"© Nathan Richard","hiImgH":1667,"hiImgW":2500,"hiUrl":"/03_hu8914030215154386966.webp","index":2,"loImgH":533,"loImgW":800,"loUrl":"/03_hu5568113574957298089.webp"},{"alt":"© Nathan Richard","hiImgH":1667,"hiImgW":2500,"hiUrl":"/02_hu7658595343359448097.webp","index":1,"loImgH":533,"loImgW":800,"loUrl":"/02_hu10443944740433921145.webp"},{"alt":"© Nathan Richard","hiImgH":3750,"hiImgW":2500,"hiUrl":"/01_hu17846552462491728064.webp","index":0,"loImgH":1200,"loImgW":800,"loUrl":"/01_hu632343605622163481.webp"}]